Workbook

Sheet Fragen Komplett
A1: Frage-ID | B1: Block | C1: Ebene | D1: Unterbereich | E1: Fragetext | F1: Owner-Dependency (OD) | G1: Deal-Blocker (DB) | H1: SOP-Trigger (SOP)
A2: F-BP-001 | B2: A | C2: Kern | D2: Block A / A1 Grundverständnis | E2: Was macht Ihr Unternehmen heute ganz konkret? (Bitte nicht allgemein, sondern operativ: Was verkaufen Sie wirklich?) | F2: Nein | G2: Ja | H2: Ja
A3: F-BP-002 | B3: A | C3: Kern | D3: Block A / A1 Grundverständnis | E3: Für wen tun Sie das? (Welche Kundentypen / Kundengruppen?) | F3: Nein | G3: Nein | H3: Nein
A4: F-BP-003 | B4: A | C4: Kern | D4: Block A / A1 Grundverständnis | E4: Warum entscheiden sich Kunden aus Ihrer Sicht für Sie – und nicht für andere? (Spontane Antwort, nicht „ideal“, sondern ehrlich.) | F4: Ja | G4: Nein | H4: Nein
A5: F-BP-004 | B5: A | C5: Kern | D5: Block A / A2 Leistung & Angebot | E5: Welche Leistungen / Produkte machen den Großteil Ihres Umsatzes aus? (Top 3 reichen.) | F5: Nein | G5: Ja | H5: Ja
A6: F-BP-005 | B6: A | C6: Kern | D6: Block A / A2 Leistung & Angebot | E6: Welche Leistungen erbringen Sie zwar – würden sie aber heute nicht mehr bewusst aufbauen? (Zeitfresser, Stress, niedrige Marge.) | F6: Ja | G6: Nein | H6: Ja
A7: F-BP-006 | B7: A | C7: Kern | D7: Block A / A3 Geld & Wirtschaftlichkeit | E7: Womit verdienen Sie gutes Geld? (Nicht „alles“, sondern konkret.) | F7: Nein | G7: Ja | H7: Ja
A8: F-BP-007 | B8: A | C8: Kern | D8: Block A / A3 Geld & Wirtschaftlichkeit | E8: Wobei fragen Sie sich selbst regelmäßig, warum Sie das überhaupt anbieten? | F8: Nein | G8: Nein | H8: Ja
A9: F-BP-008 | B9: A | C9: Workspace | D9: Block A / A4 Positionierung & Wettbewerb | E9: Wie würden Sie sich selbst am Markt einordnen? (Preis/Qualität/Service/Spezialisierung/Verfügbarkeit/Sonstiges) | F9: Nein | G9: Nein | H9: Nein
A10: F-BP-011 | B10: A | C10: Workspace | D10: Block A / A5 Kundenzugang & Nachfrage | E10: Wie kommen heute neue Kunden zu Ihnen? (Empfehlung, Anfrage, aktiv, zufällig, Plattformen etc.) | F10: Ja | G10: Nein | H10: Ja
A11: F-BP-012 | B11: A | C11: Workspace | D11: Block A / A5 Kundenzugang & Nachfrage | E11: Welche Anfragen passen gut zu Ihnen – und welche eigentlich nicht? | F11: Ja | G11: Nein | H11: Ja
A12: F-BP-015 | B12: B | C12: Kern | D12: Block B / B1 Führungsstruktur | E12: Wer trifft bei Ihnen die wichtigsten Entscheidungen im Unternehmen? (Bitte konkret benennen, nicht „wir gemeinsam“.) | F12: Ja | G12: Nein | H12: Ja
... A74: F-BP-091 | B74: I | C74: Workspace | D74: Block I / I6 Externe Wahrnehmung | E74: Wie transparent und nachvollziehbar wäre die Struktur für Dritte? | F74: Nein | G74: Nein | H74: Nein

Sheet KO Liste
A1: Frage-ID | B1: Block | C1: Ebene | D1: Unterbereich | E1: Fragetext | F1: KO_Hart | G1: KO_Soft
A2: F-BP-001 | B2: A | C2: Kern | D2: Block A / A1 Grundverständnis | E2: Was macht Ihr Unternehmen heute ganz konkret? (Bitte nicht allgemein, sondern operativ: Was verkaufen Sie wirklich?) | F2: Ja | G2: Nein
A3: F-BP-002 | B3: A | C3: Kern | D3: Block A / A1 Grundverständnis | E3: Für wen tun Sie das? (Welche Kundentypen / Kundengruppen?) | F3: Nein | G3: Ja
A4: F-BP-003 | B4: A | C4: Kern | D4: Block A / A1 Grundverständnis | E4: Warum entscheiden sich Kunden aus Ihrer Sicht für Sie – und nicht für andere? (Spontane Antwort, nicht „ideal“, sondern ehrlich.) | F4: Nein | G4: Ja
A5: F-BP-004 | B5: A | C5: Kern | D5: Block A / A2 Leistung & Angebot | E5: Welche Leistungen / Produkte machen den Großteil Ihres Umsatzes aus? (Top 3 reichen.) | F5: Ja | G5: Nein
A6: F-BP-005 | B6: A | C6: Kern | D6: Block A / A2 Leistung & Angebot | E6: Welche Leistungen erbringen Sie zwar – würden sie aber heute nicht mehr bewusst aufbauen? (Zeitfresser, Stress, niedrige Marge.) | F6: Nein | G6: Ja
A7: F-BP-006 | B7: A | C7: Kern | D7: Block A / A3 Geld & Wirtschaftlichkeit | E7: Womit verdienen Sie gutes Geld? (Nicht „alles“, sondern konkret.) | F7: Ja | G7: Nein
A8: F-BP-007 | B8: A | C8: Kern | D8: Block A / A3 Geld & Wirtschaftlichkeit | E8: Wobei fragen Sie sich selbst regelmäßig, warum Sie das überhaupt anbieten? | F8: Nein | G8: Ja
A9: F-BP-008 | B9: A | C9: Workspace | D9: Block A / A4 Positionierung & Wettbewerb | E9: Wie würden Sie sich selbst am Markt einordnen? (Preis/Qualität/Service/Spezialisierung/Verfügbarkeit/Sonstiges) | F9: Nein | G9: Ja
A10: F-BP-011 | B10: A | C10: Workspace | D10: Block A / A5 Kundenzugang & Nachfrage | E10: Wie kommen heute neue Kunden zu Ihnen? (Empfehlung, Anfrage, aktiv, zufällig, Plattformen etc.) | F10: Nein | G10: Ja
A11: F-BP-012 | B11: A | C11: Workspace | D11: Block A / A5 Kundenzugang & Nachfrage | E11: Welche Anfragen passen gut zu Ihnen – und welche eigentlich nicht? | F11: Nein | G11: Ja
A12: F-BP-015 | B12: B | C12: Kern | D12: Block B / B1 Führungsstruktur | E12: Wer trifft bei Ihnen die wichtigsten Entscheidungen im Unternehmen? (Bitte konkret benennen, nicht „wir gemeinsam“.) | F12: Nein | G12: Ja
... A74: F-BP-091 | B74: I | C74: Workspace | D74: Block I / I6 Externe Wahrnehmung | E74: Wie transparent und nachvollziehbar wäre die Struktur für Dritte? | F74: Nein | G74: Ja

Sheet Block Gewichte
A1: Block | B1: Gewicht | D1: Status
A2: A | B2: 1.2 | D2: 0 – Nicht vorhanden | E2: 0
A3: B | B3: 1.5 | D3: 1 – Kritisch | E3: 1
A4: C | B4: 1.5 | D4: 2 – Schwach | E4: 2
A5: D | B5: 1.3 | D5: 3 – OK | E5: 3
A6: E | B6: 1 | D6: 4 – Robust | E6: 4
A7: F | B7: 1.2
A8: G | B8: 1.1
A9: H | B9: 1
A10: I | B10: 1.4

Sheet Scoring
A1: Frage-ID | B1: Block | C1: OwnerDep (OD) | D1: DealRisk (DR) | E1: SOP_Relevanz (SR) | F1: KO_Flag | G1: Gewicht_Block | H1: Gewicht_Gesamt | I1: Status | J1: Gap | K1: Base Score | L1: Priority Score
A2: ='Fragen Komplett'!A2 -> F-BP-001 | B2: ='Fragen Komplett'!B2 -> A | C2: =IF('Fragen Komplett'!F2="Ja",3,0) -> 0 | D2: =IF('Fragen Komplett'!G2="Ja",3,0) -> 3 | E2: =IF('Fragen Komplett'!H2="Ja",3,0) -> 3 | F2: =IF('KO Liste'!F2="Ja",2,IF('KO Liste'!G2="Ja",1,0)) -> 2 | G2: =_xlfn.XLOOKUP(B2,'Block Gewichte'!$A:$A,'Block Gewichte'!$B:$B,1) -> 1.2 | H2: =_xlfn.LET(_xlpm.basis,(C2+D2+E2)/3,_xlpm.ko,IF(F2=2,1.75,IF(F2=1,1.25,1)),_xlpm.basis*G2*_xlpm.ko) -> 4.2 | I2: 0 | J2: =(4-I2)/4 -> 1 | K2: =H2*(C2+D2+E2) -> 25.2 | L2: =K2*J2*F2 -> 50.4
A3: ='Fragen Komplett'!A3 -> F-BP-002 | B3: ='Fragen Komplett'!B3 -> A | C3: =IF('Fragen Komplett'!F3="Ja",3,0) -> 0 | D3: =IF('Fragen Komplett'!G3="Ja",3,0) -> 0 | E3: =IF('Fragen Komplett'!H3="Ja",3,0) -> 0 | F3: =IF('KO Liste'!F3="Ja",2,IF('KO Liste'!G3="Ja",1,0)) -> 1 | G3: =_xlfn.XLOOKUP(B3,'Block Gewichte'!$A:$A,'Block Gewichte'!$B:$B,1) -> 1.2 | H3: =_xlfn.LET(_xlpm.basis,(C3+D3+E3)/3,_xlpm.ko,IF(F3=2,1.75,IF(F3=1,1.25,1)),_xlpm.basis*G3*_xlpm.ko) -> 0 | I3: 0 | J3: =(4-I3)/4 -> 1 | K3: =H3*(C3+D3+E3) -> 0 | L3: =K3*J3*F3 -> 0
A4: ='Fragen Komplett'!A4 -> F-BP-003 | B4: ='Fragen Komplett'!B4 -> A | C4: =IF('Fragen Komplett'!F4="Ja",3,0) -> 3 | D4: =IF('Fragen Komplett'!G4="Ja",3,0) -> 0 | E4: =IF('Fragen Komplett'!H4="Ja",3,0) -> 0 | F4: =IF('KO Liste'!F4="Ja",2,IF('KO Liste'!G4="Ja",1,0)) -> 1 | G4: =_xlfn.XLOOKUP(B4,'Block Gewichte'!$A:$A,'Block Gewichte'!$B:$B,1) -> 1.2 | H4: =_xlfn.LET(_xlpm.basis,(C4+D4+E4)/3,_xlpm.ko,IF(F4=2,1.75,IF(F4=1,1.25,1)),_xlpm.basis*G4*_xlpm.ko) -> 1.5 | I4: 0 | J4: =(4-I4)/4 -> 1 | K4: =H4*(C4+D4+E4) -> 4.5 | L4: =K4*J4*F4 -> 4.5
A5: ='Fragen Komplett'!A5 -> F-BP-004 | B5: ='Fragen Komplett'!B5 -> A | C5: =IF('Fragen Komplett'!F5="Ja",3,0) -> 0 | D5: =IF('Fragen Komplett'!G5="Ja",3,0) -> 3 | E5: =IF('Fragen Komplett'!H5="Ja",3,0) -> 3 | F5: =IF('KO Liste'!F5="Ja",2,IF('KO Liste'!G5="Ja",1,0)) -> 2 | G5: =_xlfn.XLOOKUP(B5,'Block Gewichte'!$A:$A,'Block Gewichte'!$B:$B,1) -> 1.2 | H5: =_xlfn.LET(_xlpm.basis,(C5+D5+E5)/3,_xlpm.ko,IF(F5=2,1.75,IF(F5=1,1.25,1)),_xlpm.basis*G5*_xlpm.ko) -> 4.2 | I5: 0 | J5: =(4-I5)/4 -> 1 | K5: =H5*(C5+D5+E5) -> 25.2 | L5: =K5*J5*F5 -> 50.4
A6: ='Fragen Komplett'!A6 -> F-BP-005 | B6: ='Fragen Komplett'!B6 -> A | C6: =IF('Fragen Komplett'!F6="Ja",3,0) -> 3 | D6: =IF('Fragen Komplett'!G6="Ja",3,0) -> 0 | E6: =IF('Fragen Komplett'!H6="Ja",3,0) -> 3 | F6: =IF('KO Liste'!F6="Ja",2,IF('KO Liste'!G6="Ja",1,0)) -> 1 | G6: =_xlfn.XLOOKUP(B6,'Block Gewichte'!$A:$A,'Block Gewichte'!$B:$B,1) -> 1.2 | H6: =_xlfn.LET(_xlpm.basis,(C6+D6+E6)/3,_xlpm.ko,IF(F6=2,1.75,IF(F6=1,1.25,1)),_xlpm.basis*G6*_xlpm.ko) -> 3 | I6: 0 | J6: =(4-I6)/4 -> 1 | K6: =H6*(C6+D6+E6) -> 18 | L6: =K6*J6*F6 -> 18
A7: ='Fragen Komplett'!A7 -> F-BP-006 | B7: ='Fragen Komplett'!B7 -> A | C7: =IF('Fragen Komplett'!F7="Ja",3,0) -> 0 | D7: =IF('Fragen Komplett'!G7="Ja",3,0) -> 3 | E7: =IF('Fragen Komplett'!H7="Ja",3,0) -> 3 | F7: =IF('KO Liste'!F7="Ja",2,IF('KO Liste'!G7="Ja",1,0)) -> 2 | G7: =_xlfn.XLOOKUP(B7,'Block Gewichte'!$A:$A,'Block Gewichte'!$B:$B,1) -> 1.2 | H7: =_xlfn.LET(_xlpm.basis,(C7+D7+E7)/3,_xlpm.ko,IF(F7=2,1.75,IF(F7=1,1.25,1)),_xlpm.basis*G7*_xlpm.ko) -> 4.2 | J7: =(4-I7)/4 -> 1 | K7: =H7*(C7+D7+E7) -> 25.2 | L7: =K7*J7*F7 -> 50.4
A8: ='Fragen Komplett'!A8 -> F-BP-007 | B8: ='Fragen Komplett'!B8 -> A | C8: =IF('Fragen Komplett'!F8="Ja",3,0) -> 0 | D8: =IF('Fragen Komplett'!G8="Ja",3,0) -> 0 | E8: =IF('Fragen Komplett'!H8="Ja",3,0) -> 3 | F8: =IF('KO Liste'!F8="Ja",2,IF('KO Liste'!G8="Ja",1,0)) -> 1 | G8: =_xlfn.XLOOKUP(B8,'Block Gewichte'!$A:$A,'Block Gewichte'!$B:$B,1) -> 1.2 | H8: =_xlfn.LET(_xlpm.basis,(C8+D8+E8)/3,_xlpm.ko,IF(F8=2,1.75,IF(F8=1,1.25,1)),_xlpm.basis*G8*_xlpm.ko) -> 1.5 | J8: =(4-I8)/4 -> 1 | K8: =H8*(C8+D8+E8) -> 4.5 | L8: =K8*J8*F8 -> 4.5
A9: ='Fragen Komplett'!A9 -> F-BP-008 | B9: ='Fragen Komplett'!B9 -> A | C9: =IF('Fragen Komplett'!F9="Ja",3,0) -> 0 | D9: =IF('Fragen Komplett'!G9="Ja",3,0) -> 0 | E9: =IF('Fragen Komplett'!H9="Ja",3,0) -> 0 | F9: =IF('KO Liste'!F9="Ja",2,IF('KO Liste'!G9="Ja",1,0)) -> 1 | G9: =_xlfn.XLOOKUP(B9,'Block Gewichte'!$A:$A,'Block Gewichte'!$B:$B,1) -> 1.2 | H9: =_xlfn.LET(_xlpm.basis,(C9+D9+E9)/3,_xlpm.ko,IF(F9=2,1.75,IF(F9=1,1.25,1)),_xlpm.basis*G9*_xlpm.ko) -> 0 | J9: =(4-I9)/4 -> 1 | K9: =H9*(C9+D9+E9) -> 0 | L9: =K9*J9*F9 -> 0
A10: ='Fragen Komplett'!A10 -> F-BP-011 | B10: ='Fragen Komplett'!B10 -> A | C10: =IF('Fragen Komplett'!F10="Ja",3,0) -> 3 | D10: =IF('Fragen Komplett'!G10="Ja",3,0) -> 0 | E10: =IF('Fragen Komplett'!H10="Ja",3,0) -> 3 | F10: =IF('KO Liste'!F10="Ja",2,IF('KO Liste'!G10="Ja",1,0)) -> 1 | G10: =_xlfn.XLOOKUP(B10,'Block Gewichte'!$A:$A,'Block Gewichte'!$B:$B,1) -> 1.2 | H10: =_xlfn.LET(_xlpm.basis,(C10+D10+E10)/3,_xlpm.ko,IF(F10=2,1.75,IF(F10=1,1.25,1)),_xlpm.basis*G10*_xlpm.ko) -> 3 | J10: =(4-I10)/4 -> 1 | K10: =H10*(C10+D10+E10) -> 18 | L10: =K10*J10*F10 -> 18
A11: ='Fragen Komplett'!A11 -> F-BP-012 | B11: ='Fragen Komplett'!B11 -> A | C11: =IF('Fragen Komplett'!F11="Ja",3,0) -> 3 | D11: =IF('Fragen Komplett'!G11="Ja",3,0) -> 0 | E11: =IF('Fragen Komplett'!H11="Ja",3,0) -> 3 | F11: =IF('KO Liste'!F11="Ja",2,IF('KO Liste'!G11="Ja",1,0)) -> 1 | G11: =_xlfn.XLOOKUP(B11,'Block Gewichte'!$A:$A,'Block Gewichte'!$B:$B,1) -> 1.2 | H11: =_xlfn.LET(_xlpm.basis,(C11+D11+E11)/3,_xlpm.ko,IF(F11=2,1.75,IF(F11=1,1.25,1)),_xlpm.basis*G11*_xlpm.ko) -> 3 | J11: =(4-I11)/4 -> 1 | K11: =H11*(C11+D11+E11) -> 18 | L11: =K11*J11*F11 -> 18
A12: ='Fragen Komplett'!A12 -> F-BP-015 | B12: ='Fragen Komplett'!B12 -> B | C12: =IF('Fragen Komplett'!F12="Ja",3,0) -> 3 | D12: =IF('Fragen Komplett'!G12="Ja",3,0) -> 0 | E12: =IF('Fragen Komplett'!H12="Ja",3,0) -> 3 | F12: =IF('KO Liste'!F12="Ja",2,IF('KO Liste'!G12="Ja",1,0)) -> 1 | G12: =_xlfn.XLOOKUP(B12,'Block Gewichte'!$A:$A,'Block Gewichte'!$B:$B,1) -> 1.5 | H12: =_xlfn.LET(_xlpm.basis,(C12+D12+E12)/3,_xlpm.ko,IF(F12=2,1.75,IF(F12=1,1.25,1)),_xlpm.basis*G12*_xlpm.ko) -> 3.75 | J12: =(4-I12)/4 -> 1 | K12: =H12*(C12+D12+E12) -> 22.5 | L12: =K12*J12*F12 -> 22.5
A13: ='Fragen Komplett'!A13 -> F-BP-016 | B13: ='Fragen Komplett'!B13 -> B | C13: =IF('Fragen Komplett'!F13="Ja",3,0) -> 3 | D13: =IF('Fragen Komplett'!G13="Ja",3,0) -> 0 | E13: =IF('Fragen Komplett'!H13="Ja",3,0) -> 3 | F13: =IF('KO Liste'!F13="Ja",2,IF('KO Liste'!G13="Ja",1,0)) -> 1 | G13: =_xlfn.XLOOKUP(B13,'Block Gewichte'!$A:$A,'Block Gewichte'!$B:$B,1) -> 1.5 | H13: =_xlfn.LET(_xlpm.basis,(C13+D13+E13)/3,_xlpm.ko,IF(F13=2,1.75,IF(F13=1,1.25,1)),_xlpm.basis*G13*_xlpm.ko) -> 3.75 | J13: =(4-I13)/4 -> 1 | K13: =H13*(C13+D13+E13) -> 22.5 | L13: =K13*J13*F13 -> 22.5
A14: ='Fragen Komplett'!A14 -> F-BP-017 | B14: ='Fragen Komplett'!B14 -> B | C14: =IF('Fragen Komplett'!F14="Ja",3,0) -> 3 | D14: =IF('Fragen Komplett'!G14="Ja",3,0) -> 0 | E14: =IF('Fragen Komplett'!H14="Ja",3,0) -> 3 | F14: =IF('KO Liste'!F14="Ja",2,IF('KO Liste'!G14="Ja",1,0)) -> 1 | G14: =_xlfn.XLOOKUP(B14,'Block Gewichte'!$A:$A,'Block Gewichte'!$B:$B,1) -> 1.5 | H14: =_xlfn.LET(_xlpm.basis,(C14+D14+E14)/3,_xlpm.ko,IF(F14=2,1.75,IF(F14=1,1.25,1)),_xlpm.basis*G14*_xlpm.ko) -> 3.75 | J14: =(4-I14)/4 -> 1 | K14: =H14*(C14+D14+E14) -> 22.5 | L14: =K14*J14*F14 -> 22.5
A15: ='Fragen Komplett'!A15 -> F-BP-018 | B15: ='Fragen Komplett'!B15 -> B | C15: =IF('Fragen Komplett'!F15="Ja",3,0) -> 3 | D15: =IF('Fragen Komplett'!G15="Ja",3,0) -> 0 | E15: =IF('Fragen Komplett'!H15="Ja",3,0) -> 3 | F15: =IF('KO Liste'!F15="Ja",2,IF('KO Liste'!G15="Ja",1,0)) -> 1 | G15: =_xlfn.XLOOKUP(B15,'Block Gewichte'!$A:$A,'Block Gewichte'!$B:$B,1) -> 1.5 | H15: =_xlfn.LET(_xlpm.basis,(C15+D15+E15)/3,_xlpm.ko,IF(F15=2,1.75,IF(F15=1,1.25,1)),_xlpm.basis*G15*_xlpm.ko) -> 3.75 | J15: =(4-I15)/4 -> 1 | K15: =H15*(C15+D15+E15) -> 22.5 | L15: =K15*J15*F15 -> 22.5
A16: ='Fragen Komplett'!A16 -> F-BP-019 | B16: ='Fragen Komplett'!B16 -> B | C16: =IF('Fragen Komplett'!F16="Ja",3,0) -> 3 | D16: =IF('Fragen Komplett'!G16="Ja",3,0) -> 0 | E16: =IF('Fragen Komplett'!H16="Ja",3,0) -> 3 | F16: =IF('KO Liste'!F16="Ja",2,IF('KO Liste'!G16="Ja",1,0)) -> 1 | G16: =_xlfn.XLOOKUP(B16,'Block Gewichte'!$A:$A,'Block Gewichte'!$B:$B,1) -> 1.5 | H16: =_xlfn.LET(_xlpm.basis,(C16+D16+E16)/3,_xlpm.ko,IF(F16=2,1.75,IF(F16=1,1.25,1)),_xlpm.basis*G16*_xlpm.ko) -> 3.75 | J16: =(4-I16)/4 -> 1 | K16: =H16*(C16+D16+E16) -> 22.5 | L16: =K16*J16*F16 -> 22.5
A17: ='Fragen Komplett'!A17 -> F-BP-020 | B17: ='Fragen Komplett'!B17 -> B | C17: =IF('Fragen Komplett'!F17="Ja",3,0) -> 3 | D17: =IF('Fragen Komplett'!G17="Ja",3,0) -> 3 | E17: =IF('Fragen Komplett'!H17="Ja",3,0) -> 3 | F17: =IF('KO Liste'!F17="Ja",2,IF('KO Liste'!G17="Ja",1,0)) -> 2 | G17: =_xlfn.XLOOKUP(B17,'Block Gewichte'!$A:$A,'Block Gewichte'!$B:$B,1) -> 1.5 | H17: =_xlfn.LET(_xlpm.basis,(C17+D17+E17)/3,_xlpm.ko,IF(F17=2,1.75,IF(F17=1,1.25,1)),_xlpm.basis*G17*_xlpm.ko) -> 7.875 | J17: =(4-I17)/4 -> 1 | K17: =H17*(C17+D17+E17) -> 70.875 | L17: =K17*J17*F17 -> 141.75
A18: ='Fragen Komplett'!A18 -> F-BP-021 | B18: ='Fragen Komplett'!B18 -> B | C18: =IF('Fragen Komplett'!F18="Ja",3,0) -> 3 | D18: =IF('Fragen Komplett'!G18="Ja",3,0) -> 0 | E18: =IF('Fragen Komplett'!H18="Ja",3,0) -> 3 | F18: =IF('KO Liste'!F18="Ja",2,IF('KO Liste'!G18="Ja",1,0)) -> 1 | G18: =_xlfn.XLOOKUP(B18,'Block Gewichte'!$A:$A,'Block Gewichte'!$B:$B,1) -> 1.5 | H18: =_xlfn.LET(_xlpm.basis,(C18+D18+E18)/3,_xlpm.ko,IF(F18=2,1.75,IF(F18=1,1.25,1)),_xlpm.basis*G18*_xlpm.ko) -> 3.75 | J18: =(4-I18)/4 -> 1 | K18: =H18*(C18+D18+E18) -> 22.5 | L18: =K18*J18*F18 -> 22.5
... A74: ='Fragen Komplett'!A74 -> F-BP-091 | B74: ='Fragen Komplett'!B74 -> I | C74: =IF('Fragen Komplett'!F74="Ja",3,0) -> 0 | D74: =IF('Fragen Komplett'!G74="Ja",3,0) -> 0 | E74: =IF('Fragen Komplett'!H74="Ja",3,0) -> 0 | F74: =IF('KO Liste'!F74="Ja",2,IF('KO Liste'!G74="Ja",1,0)) -> 1 | G74: =_xlfn.XLOOKUP(B74,'Block Gewichte'!$A:$A,'Block Gewichte'!$B:$B,1) -> 1.4 | H74: =_xlfn.LET(_xlpm.basis,(C74+D74+E74)/3,_xlpm.ko,IF(F74=2,1.75,IF(F74=1,1.25,1)),_xlpm.basis*G74*_xlpm.ko) -> 0 | J74: =(4-I74)/4 -> 1 | K74: =H74*(C74+D74+E74) -> 0 | L74: =K74*J74*F74 -> 0

Sheet Scorecard
